bucket3/__init__.py
bucket3/b3tools.py
bucket3/bucket.py
bucket3/fsmeta.py
bucket3/test.py
bucket3/conf/conf.example.yaml
bucket3/conf/post.example.md
bucket3/default/skel/404.html
bucket3/default/skel/robots.txt
bucket3/default/skel/assets/css/bootstrap-theme.css
bucket3/default/skel/assets/css/bootstrap-theme.min.css
bucket3/default/skel/assets/css/bootstrap.css
bucket3/default/skel/assets/css/bootstrap.min.css
bucket3/default/skel/assets/css/bucket3.css
bucket3/default/skel/assets/img/bucket3.jpg
bucket3/default/skel/assets/img/bucket3_small.jpg
bucket3/default/skel/assets/img/favicon.ico
bucket3/default/skel/assets/js/bootstrap.js
bucket3/default/skel/assets/js/bootstrap.min.js
bucket3/default/templates/archive.html
bucket3/default/templates/base.html
bucket3/default/templates/home.html
bucket3/default/templates/main_archive.html
bucket3/default/templates/post.html
bucket3/default/templates/rss.xml
bucket3/default/templates/sitemap.xml
bucket3/default/templates/tag_cloud.html
bucket3-0.16.1.data/scripts/bucket3
bucket3-0.16.1.dist-info/METADATA
bucket3-0.16.1.dist-info/WHEEL
bucket3-0.16.1.dist-info/top_level.txt
bucket3-0.16.1.dist-info/RECORD
