Metadata-Version: 2.1
Name: bucket3
Version: 0.16.1
Summary: Static blog generator.
Home-page: http://www.bucket3.com/
Author: Panayotis Vryonis
Author-email: vrypan@gmail.com
License: MIT-LICENSE.txt
Platform: UNKNOWN
Classifier: Development Status :: 4 - Beta
Classifier: Environment :: Console
Classifier: License :: OSI Approved :: MIT License
Classifier: Operating System :: OS Independent
Classifier: Programming Language :: Python :: 3
Classifier: Topic :: Internet :: WWW/HTTP
Classifier: Topic :: Software Development :: Libraries :: Python Modules
Requires-Dist: markdown
Requires-Dist: py-gfm
Requires-Dist: Jinja2
Requires-Dist: PyYAML
Requires-Dist: docopt
Requires-Dist: unidecode
Requires-Dist: htmlmin
Requires-Dist: lxml
